{"artists": [{"external_urls": {"spotify": "https://open.spotify.com/artist/2uYWxilOVlUdk4oV9DvwqK"}, "followers": {"href": null, "total": 10763102}, "genres": [], "href": "https://api.spotify.com/v1/artists/2uYWxilOVlUdk4oV9DvwqK", "id": "2uYWxilOVlUdk4oV9DvwqK", "images": [{"url": "https://i.scdn.co/image/ab6761610000e5eb4bdb3888818637acb71c4a13", "height": 640, "width": 640}, {"url": "https://i.scdn.co/image/ab676161000051744bdb3888818637acb71c4a13", "height": 320, "width": 320}, {"url": "https://i.scdn.co/image/ab6761610000f1784bdb3888818637acb71c4a13", "height": 160, "width": 160}], "name": "Mitski", "popularity": 82, "type": "artist", "uri": "spotify:artist:2uYWxilOVlUdk4oV9DvwqK"}, {"external_urls": {"spotify": "https://open.spotify.com/artist/4xtWjIlVuZwTCeqVAsgEXy"}, "followers": {"href": null, "total": 1988425}, "genres": ["horrorcore", "rap rock"], "href": "https://api.spotify.com/v1/artists/4xtWjIlVuZwTCeqVAsgEXy", "id": "4xtWjIlVuZwTCeqVAsgEXy", "images": [{"url": "https://i.scdn.co/image/ab6761610000e5eb534c6d647953f20279d654f8", "height": 640, "width": 640}, {"url": "https://i.scdn.co/image/ab67616100005174534c6d647953f20279d654f8", "height": 320, "width": 320}, {"url": "https://i.scdn.co/image/ab6761610000f178534c6d647953f20279d654f8", "height": 160, "width": 160}], "name": "Insane Clown Posse", "popularity": 68, "type": "artist", "uri": "spotify:artist:4xtWjIlVuZwTCeqVAsgEXy"}, {"external_urls": {"spotify": "https://open.spotify.com/artist/61if35zz1W11GejEkxTLEQ"}, "followers": {"href": null, "total": 4694019}, "genres": ["bollywood", "desi", "hindi pop"], "href": "https://api.spotify.com/v1/artists/61if35zz1W11GejEkxTLEQ", "id": "61if35zz1W11GejEkxTLEQ", "images": [{"url": "https://i.scdn.co/image/ab6761610000e5ebc88897f144b4df438ec58727", "height": 640, "width": 640}, {"url": "https://i.scdn.co/image/ab67616100005174c88897f144b4df438ec58727", "height": 320, "width": 320}, {"url": "https://i.scdn.co/image/ab6761610000f178c88897f144b4df438ec58727", "height": 160, "width": 160}], "name": "Benny Dayal", "popularity": 73, "type": "artist", "uri": "spotify:artist:61if35zz1W11GejEkxTLEQ"}, {"external_urls": {"spotify": "https://open.spotify.com/artist/1Jt7JB3WIWaANzwHoybsVn"}, "followers": {"href": null, "total": 286939}, "genres": ["bollywood", "desi", "hindi pop"], "href": "https://api.spotify.com/v1/artists/1Jt7JB3WIWaANzwHoybsVn", "id": "1Jt7JB3WIWaANzwHoybsVn", "images": [{"url": "https://i.scdn.co/image/ab6761610000e5eb2a21402b52d3cc09b79acd07", "height": 640, "width": 640}, {"url": "https://i.scdn.co/image/ab676161000051742a21402b52d3cc09b79acd07", "height": 320, "width": 320}, {"url": "https://i.scdn.co/image/ab6761610000f1782a21402b52d3cc09b79acd07", "height": 160, "width": 160}], "name": "Shefali Alvares", "popularity": 62, "type": "artist", "uri": "spotify:artist:1Jt7JB3WIWaANzwHoybsVn"}, {"external_urls": {"spotify": "https://open.spotify.com/artist/6CXEwIaXYfVJ84biCxqc9k"}, "followers": {"href": null, "total": 12031770}, "genres": ["bollywood", "desi", "hindi pop"], "href": "https://api.spotify.com/v1/artists/6CXEwIaXYfVJ84biCxqc9k", "id": "6CXEwIaXYfVJ84biCxqc9k", "images": [{"url": "https://i.scdn.co/image/ab6761610000e5eb76328e37a2c1280ab9adb90c", "height": 640, "width": 640}, {"url": "https://i.scdn.co/image/ab6761610000517476328e37a2c1280ab9adb90c", "height": 320, "width": 320}, {"url": "https://i.scdn.co/image/ab6761610000f17876328e37a2c1280ab9adb90c", "height": 160, "width": 160}], "name": "Vishal Dadlani", "popularity": 76, "type": "artist", "uri": "spotify:artist:6CXEwIaXYfVJ84biCxqc9k"}, {"external_urls": {"spotify": "https://open.spotify.com/artist/4YRxDV8wJFPHPTeXepOstw"}, "followers": {"href": null, "total": 155907872}, "genres": ["hindi pop", "bollywood", "desi", "bangla pop"], "href": "https://api.spotify.com/v1/artists/4YRxDV8wJFPHPTeXepOstw", "id": "4YRxDV8wJFPHPTeXepOstw", "images": [{"url": "https://i.scdn.co/image/ab6761610000e5eb5ba2d75eb08a2d672f9b69b7", "height": 640, "width": 640}, {"url": "https://i.scdn.co/image/ab676161000051745ba2d75eb08a2d672f9b69b7", "height": 320, "width": 320}, {"url": "https://i.scdn.co/image/ab6761610000f1785ba2d75eb08a2d672f9b69b7", "height": 160, "width": 160}], "name": "Arijit Singh", "popularity": 93, "type": "artist", "uri": "spotify:artist:4YRxDV8wJFPHPTeXepOstw"}, {"external_urls": {"spotify": "https://open.spotify.com/artist/6XypcJDBmfuRjq52PFUVwd"}, "followers": {"href": null, "total": 461176}, "genres": ["marathi pop", "gujarati garba", "gujarati pop"], "href": "https://api.spotify.com/v1/artists/6XypcJDBmfuRjq52PFUVwd", "id": "6XypcJDBmfuRjq52PFUVwd", "images": [{"url": "https://i.scdn.co/image/ab6761610000e5eb60df9e370aa1272448e5d80a", "height": 640, "width": 640}, {"url": "https://i.scdn.co/image/ab6761610000517460df9e370aa1272448e5d80a", "height": 320, "width": 320}, {"url": "https://i.scdn.co/image/ab6761610000f17860df9e370aa1272448e5d80a", "height": 160, "width": 160}], "name": "Rahul Vaidya", "popularity": 49, "type": "artist", "uri": "spotify:artist:6XypcJDBmfuRjq52PFUVwd"}, {"external_urls": {"spotify": "https://open.spotify.com/artist/1wRPtKGflJrBx9BmLsSwlU"}, "followers": {"href": null, "total": 55865929}, "genres": ["bollywood", "hindi pop", "desi"], "href": "https://api.spotify.com/v1/artists/1wRPtKGflJrBx9BmLsSwlU", "id": "1wRPtKGflJrBx9BmLsSwlU", "images": [{"url": "https://i.scdn.co/image/ab6761610000e5ebcb6926f44f620555ba444fca", "height": 640, "width": 640}, {"url": "https://i.scdn.co/image/ab67616100005174cb6926f44f620555ba444fca", "height": 320, "width": 320}, {"url": "https://i.scdn.co/image/ab6761610000f178cb6926f44f620555ba444fca", "height": 160, "width": 160}], "name": "Pritam", "popularity": 91, "type": "artist", "uri": "spotify:artist:1wRPtKGflJrBx9BmLsSwlU"}, {"external_urls": {"spotify": "https://open.spotify.com/artist/6Mv8GjQa7LKUGCAqa9qqdb"}, "followers": {"href": null, "total": 14637466}, "genres": ["bollywood", "desi", "hindi pop"], "href": "https://api.spotify.com/v1/artists/6Mv8GjQa7LKUGCAqa9qqdb", "id": "6Mv8GjQa7LKUGCAqa9qqdb", "images": [{"url": "https://i.scdn.co/image/ab6761610000e5eb90b6c3d093f9b02aad628eaf", "height": 640, "width": 640}, {"url": "https://i.scdn.co/image/ab6761610000517490b6c3d093f9b02aad628eaf", "height": 320, "width": 320}, {"url": "https://i.scdn.co/image/ab6761610000f17890b6c3d093f9b02aad628eaf", "height": 160, "width": 160}], "name": "Vishal-Shekhar", "popularity": 82, "type": "artist", "uri": "spotify:artist:6Mv8GjQa7LKUGCAqa9qqdb"}, {"external_urls": {"spotify": "https://open.spotify.com/artist/1TbRSunWGZ46mqnapcWxrm"}, "followers": {"href": null, "total": 1188078}, "genres": ["bollywood", "sufi", "hindi pop", "desi"], "href": "https://api.spotify.com/v1/artists/1TbRSunWGZ46mqnapcWxrm", "id": "1TbRSunWGZ46mqnapcWxrm", "images": [{"url": "https://i.scdn.co/image/ab6761610000e5eb581dae648c1a3e2978a07265", "height": 640, "width": 640}, {"url": "https://i.scdn.co/image/ab67616100005174581dae648c1a3e2978a07265", "height": 320, "width": 320}, {"url": "https://i.scdn.co/image/ab6761610000f178581dae648c1a3e2978a07265", "height": 160, "width": 160}], "name": "Salim Merchant", "popularity": 65, "type": "artist", "uri": "spotify:artist:1TbRSunWGZ46mqnapcWxrm"}, {"external_urls": {"spotify": "https://open.spotify.com/artist/70B80Lwx2sxti0M1Ng9e8K"}, "followers": {"href": null, "total": 20539941}, "genres": ["bollywood", "hindi pop", "desi"], "href": "https://api.spotify.com/v1/artists/70B80Lwx2sxti0M1Ng9e8K", "id": "70B80Lwx2sxti0M1Ng9e8K", "images": [{"url": "https://i.scdn.co/image/ab6761610000e5eb8de0e6e7e55d7773931ab7f4", "height": 640, "width": 640}, {"url": "https://i.scdn.co/image/ab676161000051748de0e6e7e55d7773931ab7f4", "height": 320, "width": 320}, {"url": "https://i.scdn.co/image/ab6761610000f1788de0e6e7e55d7773931ab7f4", "height": 160, "width": 160}], "name": "Udit Narayan", "popularity": 84, "type": "artist", "uri": "spotify:artist:70B80Lwx2sxti0M1Ng9e8K"}, {"external_urls": {"spotify": "https://open.spotify.com/artist/4LnYRxNZVCTsDCO2xKjOn8"}, "followers": {"href": null, "total": 320712}, "genres": ["bollywood", "desi", "hindi pop"], "href": "https://api.spotify.com/v1/artists/4LnYRxNZVCTsDCO2xKjOn8", "id": "4LnYRxNZVCTsDCO2xKjOn8", "images": [{"url": "https://i.scdn.co/image/ab6761610000e5eb05e1703f04ed4b3cffee256f", "height": 640, "width": 640}, {"url": "https://i.scdn.co/image/ab6761610000517405e1703f04ed4b3cffee256f", "height": 320, "width": 320}, {"url": "https://i.scdn.co/image/ab6761610000f17805e1703f04ed4b3cffee256f", "height": 160, "width": 160}], "name": "Shahid Mallya", "popularity": 61, "type": "artist", "uri": "spotify:artist:4LnYRxNZVCTsDCO2xKjOn8"}, {"external_urls": {"spotify": "https://open.spotify.com/artist/3eDT9fwXKuHWFvgZaaYC5v"}, "followers": {"href": null, "total": 17388665}, "genres": ["bollywood", "desi", "hindi pop"], "href": "https://api.spotify.com/v1/artists/3eDT9fwXKuHWFvgZaaYC5v", "id": "3eDT9fwXKuHWFvgZaaYC5v", "images": [{"url": "https://i.scdn.co/image/ab6761610000e5eba45f7ef3e1c982461f2dad6b", "height": 640, "width": 640}, {"url": "https://i.scdn.co/image/ab67616100005174a45f7ef3e1c982461f2dad6b", "height": 320, "width": 320}, {"url": "https://i.scdn.co/image/ab6761610000f178a45f7ef3e1c982461f2dad6b", "height": 160, "width": 160}], "name": "Sunidhi Chauhan", "popularity": 78, "type": "artist", "uri": "spotify:artist:3eDT9fwXKuHWFvgZaaYC5v"}, {"external_urls": {"spotify": "https://open.spotify.com/artist/4xd7mLI7urqrxELaXhAvzw"}, "followers": {"href": null, "total": 1792079}, "genres": ["bollywood", "hindi pop", "desi"], "href": "https://api.spotify.com/v1/artists/4xd7mLI7urqrxELaXhAvzw", "id": "4xd7mLI7urqrxELaXhAvzw", "images": [{"url": "https://i.scdn.co/image/ab6761610000e5eb8739e00cd15c969f86ff48a6", "height": 640, "width": 640}, {"url": "https://i.scdn.co/image/ab676161000051748739e00cd15c969f86ff48a6", "height": 320, "width": 320}, {"url": "https://i.scdn.co/image/ab6761610000f1788739e00cd15c969f86ff48a6", "height": 160, "width": 160}], "name": "Shekhar Ravjiani", "popularity": 70, "type": "artist", "uri": "spotify:artist:4xd7mLI7urqrxELaXhAvzw"}, {"external_urls": {"spotify": "https://open.spotify.com/artist/1SJOL9HJ08YOn92lFcYf8a"}, "followers": {"href": null, "total": 12649116}, "genres": ["marathi pop", "bollywood", "devotional", "bhajan", "desi", "tamil dance", "hindi pop", "tamil pop"], "href": "https://api.spotify.com/v1/artists/1SJOL9HJ08YOn92lFcYf8a", "id": "1SJOL9HJ08YOn92lFcYf8a", "images": [{"url": "https://i.scdn.co/image/ab6761610000e5eb3f27a828c24d73cf0427e2e7", "height": 640, "width": 640}, {"url": "https://i.scdn.co/image/ab676161000051743f27a828c24d73cf0427e2e7", "height": 320, "width": 320}, {"url": "https://i.scdn.co/image/ab6761610000f1783f27a828c24d73cf0427e2e7", "height": 160, "width": 160}], "name": "Shankar Mahadevan", "popularity": 79, "type": "artist", "uri": "spotify:artist:1SJOL9HJ08YOn92lFcYf8a"}, {"external_urls": {"spotify": "https://open.spotify.com/artist/5T2I75UlGBcWd5nVyfmL13"}, "followers": {"href": null, "total": 9906925}, "genres": ["bollywood", "desi", "hindi pop"], "href": "https://api.spotify.com/v1/artists/5T2I75UlGBcWd5nVyfmL13", "id": "5T2I75UlGBcWd5nVyfmL13", "images": [{"url": "https://i.scdn.co/image/ab6761610000e5eb4f6cee8d7f3c9e35f88c1cc9", "height": 640, "width": 640}, {"url": "https://i.scdn.co/image/ab676161000051744f6cee8d7f3c9e35f88c1cc9", "height": 320, "width": 320}, {"url": "https://i.scdn.co/image/ab6761610000f1784f6cee8d7f3c9e35f88c1cc9", "height": 160, "width": 160}], "name": "Mika Singh", "popularity": 69, "type": "artist", "uri": "spotify:artist:5T2I75UlGBcWd5nVyfmL13"}, {"external_urls": {"spotify": "https://open.spotify.com/artist/3GdSQUH1BRtl9UrrtuwJlP"}, "followers": {"href": null, "total": 147344}, "genres": ["bollywood", "hindi pop", "desi", "sufi"], "href": "https://api.spotify.com/v1/artists/3GdSQUH1BRtl9UrrtuwJlP", "id": "3GdSQUH1BRtl9UrrtuwJlP", "images": [{"url": "https://i.scdn.co/image/ab6761610000e5eb47b943824370b9eb2fb9607f", "height": 640, "width": 640}, {"url": "https://i.scdn.co/image/ab6761610000517447b943824370b9eb2fb9607f", "height": 320, "width": 320}, {"url": "https://i.scdn.co/image/ab6761610000f17847b943824370b9eb2fb9607f", "height": 160, "width": 160}], "name": "Irshad Kamil", "popularity": 84, "type": "artist", "uri": "spotify:artist:3GdSQUH1BRtl9UrrtuwJlP"}, {"external_urls": {"spotify": "https://open.spotify.com/artist/2CkrXQPoBz8jTQ3u0ZeLPh"}, "followers": {"href": null, "total": 1763985}, "genres": ["indian indie", "hindi hip hop", "hindi indie", "desi hip hop", "desi", "bollywood"], "href": "https://api.spotify.com/v1/artists/2CkrXQPoBz8jTQ3u0ZeLPh", "id": "2CkrXQPoBz8jTQ3u0ZeLPh", "images": [{"url": "https://i.scdn.co/image/ab6761610000e5ebb189e052ae23f2278af3fef6", "height": 640, "width": 640}, {"url": "https://i.scdn.co/image/ab67616100005174b189e052ae23f2278af3fef6", "height": 320, "width": 320}, {"url": "https://i.scdn.co/image/ab6761610000f178b189e052ae23f2278af3fef6", "height": 160, "width": 160}], "name": "Nucleya", "popularity": 52, "type": "artist", "uri": "spotify:artist:2CkrXQPoBz8jTQ3u0ZeLPh"}, {"external_urls": {"spotify": "https://open.spotify.com/artist/76fuWYgIf3TVIopTs3vaJ6"}, "followers": {"href": null, "total": 5042687}, "genres": ["bollywood", "hindi pop", "desi"], "href": "https://api.spotify.com/v1/artists/76fuWYgIf3TVIopTs3vaJ6", "id": "76fuWYgIf3TVIopTs3vaJ6", "images": [{"url": "https://i.scdn.co/image/ab6761610000e5ebc1559c29cb61d249075a8b86", "height": 640, "width": 640}, {"url": "https://i.scdn.co/image/ab67616100005174c1559c29cb61d249075a8b86", "height": 320, "width": 320}, {"url": "https://i.scdn.co/image/ab6761610000f178c1559c29cb61d249075a8b86", "height": 160, "width": 160}], "name": "Amaal Mallik", "popularity": 73, "type": "artist", "uri": "spotify:artist:76fuWYgIf3TVIopTs3vaJ6"}, {"external_urls": {"spotify": "https://open.spotify.com/artist/4f7KfxeHq9BiylGmyXepGt"}, "followers": {"href": null, "total": 5414588}, "genres": ["bollywood", "hindi pop", "desi", "desi pop", "gujarati garba"], "href": "https://api.spotify.com/v1/artists/4f7KfxeHq9BiylGmyXepGt", "id": "4f7KfxeHq9BiylGmyXepGt", "images": [{"url": "https://i.scdn.co/image/ab6761610000e5eb96f049daefd1875282baab0a", "height": 640, "width": 640}, {"url": "https://i.scdn.co/image/ab6761610000517496f049daefd1875282baab0a", "height": 320, "width": 320}, {"url": "https://i.scdn.co/image/ab6761610000f17896f049daefd1875282baab0a", "height": 160, "width": 160}], "name": "Tanishk Bagchi", "popularity": 84, "type": "artist", "uri": "spotify:artist:4f7KfxeHq9BiylGmyXepGt"}, {"external_urls": {"spotify": "https://open.spotify.com/artist/0y59o4v8uw5crbN9M3JiL1"}, "followers": {"href": null, "total": 30150965}, "genres": ["bollywood", "desi", "hindi pop", "desi hip hop", "hindi hip hop", "desi pop"], "href": "https://api.spotify.com/v1/artists/0y59o4v8uw5crbN9M3JiL1", "id": "0y59o4v8uw5crbN9M3JiL1", "images": [{"url": "https://i.scdn.co/image/ab6761610000e5eb7b386b1320742bd6686854e7", "height": 640, "width": 640}, {"url": "https://i.scdn.co/image/ab676161000051747b386b1320742bd6686854e7", "height": 320, "width": 320}, {"url": "https://i.scdn.co/image/ab6761610000f1787b386b1320742bd6686854e7", "height": 160, "width": 160}], "name": "Badshah", "popularity": 78, "type": "artist", "uri": "spotify:artist:0y59o4v8uw5crbN9M3JiL1"}, {"external_urls": {"spotify": "https://open.spotify.com/artist/6jf2eKjiPT6P18RbOSLzf0"}, "followers": {"href": null, "total": 1165884}, "genres": ["hindi pop", "bollywood", "bangla pop", "desi pop"], "href": "https://api.spotify.com/v1/artists/6jf2eKjiPT6P18RbOSLzf0", "id": "6jf2eKjiPT6P18RbOSLzf0", "images": [{"url": "https://i.scdn.co/image/ab6761610000e5eb37b6000b2144130f3a19df41", "height": 640, "width": 640}, {"url": "https://i.scdn.co/image/ab6761610000517437b6000b2144130f3a19df41", "height": 320, "width": 320}, {"url": "https://i.scdn.co/image/ab6761610000f17837b6000b2144130f3a19df41", "height": 160, "width": 160}], "name": "Arko", "popularity": 68, "type": "artist", "uri": "spotify:artist:6jf2eKjiPT6P18RbOSLzf0"}, {"external_urls": {"spotify": "https://open.spotify.com/artist/4IKVDbCSBTxBeAsMKjAuTs"}, "followers": {"href": null, "total": 23356526}, "genres": ["bollywood", "hindi pop", "kannada pop", "tollywood", "telugu pop"], "href": "https://api.spotify.com/v1/artists/4IKVDbCSBTxBeAsMKjAuTs", "id": "4IKVDbCSBTxBeAsMKjAuTs", "images": [{"url": "https://i.scdn.co/image/ab6761610000e5eb304d3dd0ed0fef6a64ba1dd7", "height": 640, "width": 640}, {"url": "https://i.scdn.co/image/ab67616100005174304d3dd0ed0fef6a64ba1dd7", "height": 320, "width": 320}, {"url": "https://i.scdn.co/image/ab6761610000f178304d3dd0ed0fef6a64ba1dd7", "height": 160, "width": 160}], "name": "Armaan Malik", "popularity": 75, "type": "artist", "uri": "spotify:artist:4IKVDbCSBTxBeAsMKjAuTs"}, {"external_urls": {"spotify": "https://open.spotify.com/artist/1sVmXkzX2ukc6QvasrDBES"}, "followers": {"href": null, "total": 4727010}, "genres": ["bollywood", "hindi pop", "gujarati garba", "desi"], "href": "https://api.spotify.com/v1/artists/1sVmXkzX2ukc6QvasrDBES", "id": "1sVmXkzX2ukc6QvasrDBES", "images": [{"url": "https://i.scdn.co/image/ab6761610000e5ebc907b6b1feb4d6b09a3fbde1", "height": 640, "width": 640}, {"url": "https://i.scdn.co/image/ab67616100005174c907b6b1feb4d6b09a3fbde1", "height": 320, "width": 320}, {"url": "https://i.scdn.co/image/ab6761610000f178c907b6b1feb4d6b09a3fbde1", "height": 160, "width": 160}], "name": "Asees Kaur", "popularity": 74, "type": "artist", "uri": "spotify:artist:1sVmXkzX2ukc6QvasrDBES"}, {"external_urls": {"spotify": "https://open.spotify.com/artist/4oaJL0V5asQDh4sqplTVhX"}, "followers": {"href": null, "total": 240968}, "genres": ["bollywood", "haryanvi pop", "desi"], "href": "https://api.spotify.com/v1/artists/4oaJL0V5asQDh4sqplTVhX", "id": "4oaJL0V5asQDh4sqplTVhX", "images": [{"url": "https://i.scdn.co/image/ab6761610000e5eb441411ad991222f51ec803d5", "height": 640, "width": 640}, {"url": "https://i.scdn.co/image/ab67616100005174441411ad991222f51ec803d5", "height": 320, "width": 320}, {"url": "https://i.scdn.co/image/ab6761610000f178441411ad991222f51ec803d5", "height": 160, "width": 160}], "name": "Fazilpuria", "popularity": 57, "type": "artist", "uri": "spotify:artist:4oaJL0V5asQDh4sqplTVhX"}, {"external_urls": {"spotify": "https://open.spotify.com/artist/3FgHkfb3IqG4WKuVe1xCXM"}, "followers": {"href": null, "total": 1259314}, "genres": ["bollywood", "desi", "hindi pop"], "href": "https://api.spotify.com/v1/artists/3FgHkfb3IqG4WKuVe1xCXM", "id": "3FgHkfb3IqG4WKuVe1xCXM", "images": [{"url": "https://i.scdn.co/image/ab6761610000e5ebaafca76e1827224f54746dc1", "height": 640, "width": 640}, {"url": "https://i.scdn.co/image/ab67616100005174aafca76e1827224f54746dc1", "height": 320, "width": 320}, {"url": "https://i.scdn.co/image/ab6761610000f178aafca76e1827224f54746dc1", "height": 160, "width": 160}], "name": "Sukriti Kakar", "popularity": 59, "type": "artist", "uri": "spotify:artist:3FgHkfb3IqG4WKuVe1xCXM"}, {"external_urls": {"spotify": "https://open.spotify.com/artist/5f4QpKfy7ptCHwTqspnSJI"}, "followers": {"href": null, "total": 48616732}, "genres": ["bollywood", "hindi pop", "desi", "desi pop", "gujarati garba"], "href": "https://api.spotify.com/v1/artists/5f4QpKfy7ptCHwTqspnSJI", "id": "5f4QpKfy7ptCHwTqspnSJI", "images": [{"url": "https://i.scdn.co/image/ab6761610000e5eb77c63908ac248d3bf6d42f27", "height": 640, "width": 640}, {"url": "https://i.scdn.co/image/ab6761610000517477c63908ac248d3bf6d42f27", "height": 320, "width": 320}, {"url": "https://i.scdn.co/image/ab6761610000f17877c63908ac248d3bf6d42f27", "height": 160, "width": 160}], "name": "Neha Kakkar", "popularity": 75, "type": "artist", "uri": "spotify:artist:5f4QpKfy7ptCHwTqspnSJI"}, {"external_urls": {"spotify": "https://open.spotify.com/artist/0LyfQWJT6nXafLPZqxe9Of"}, "followers": {"href": null, "total": 2744724}, "genres": [], "href": "https://api.spotify.com/v1/artists/0LyfQWJT6nXafLPZqxe9Of", "id": "0LyfQWJT6nXafLPZqxe9Of", "images": [{"url": "https://i.scdn.co/image/ab6761610000e5eb6b134287e3095d2c84b7932a", "height": 640, "width": 640}, {"url": "https://i.scdn.co/image/ab676161000051746b134287e3095d2c84b7932a", "height": 320, "width": 320}, {"url": "https://i.scdn.co/image/ab6761610000f1786b134287e3095d2c84b7932a", "height": 160, "width": 160}], "name": "Various Artists", "popularity": 0, "type": "artist", "uri": "spotify:artist:0LyfQWJT6nXafLPZqxe9Of"}, {"external_urls": {"spotify": "https://open.spotify.com/artist/0oOet2f43PA68X5RxKobEy"}, "followers": {"href": null, "total": 31636404}, "genres": ["bollywood", "hindi pop", "desi", "kannada pop", "marathi pop"], "href": "https://api.spotify.com/v1/artists/0oOet2f43PA68X5RxKobEy", "id": "0oOet2f43PA68X5RxKobEy", "images": [{"url": "https://i.scdn.co/image/ab6761610000e5eb59303d54ce789210e745e1a9", "height": 640, "width": 640}, {"url": "https://i.scdn.co/image/ab6761610000517459303d54ce789210e745e1a9", "height": 320, "width": 320}, {"url": "https://i.scdn.co/image/ab6761610000f17859303d54ce789210e745e1a9", "height": 160, "width": 160}], "name": "Shreya Ghoshal", "popularity": 88, "type": "artist", "uri": "spotify:artist:0oOet2f43PA68X5RxKobEy"}, {"external_urls": {"spotify": "https://open.spotify.com/artist/0XL6ie7a0NY5FM05b9Rn5L"}, "followers": {"href": null, "total": 4005620}, "genres": ["bollywood", "desi", "hindi pop"], "href": "https://api.spotify.com/v1/artists/0XL6ie7a0NY5FM05b9Rn5L", "id": "0XL6ie7a0NY5FM05b9Rn5L", "images": [{"url": "https://i.scdn.co/image/ab6761610000e5eb78fefd14590f399d13d035a9", "height": 640, "width": 640}, {"url": "https://i.scdn.co/image/ab6761610000517478fefd14590f399d13d035a9", "height": 320, "width": 320}, {"url": "https://i.scdn.co/image/ab6761610000f17878fefd14590f399d13d035a9", "height": 160, "width": 160}], "name": "Farhan Akhtar", "popularity": 58, "type": "artist", "uri": "spotify:artist:0XL6ie7a0NY5FM05b9Rn5L"}, {"external_urls": {"spotify": "https://open.spotify.com/artist/5TWDvkVWG1vayan1QA9q8U"}, "followers": {"href": null, "total": 450021}, "genres": ["bollywood", "desi", "hindi pop"], "href": "https://api.spotify.com/v1/artists/5TWDvkVWG1vayan1QA9q8U", "id": "5TWDvkVWG1vayan1QA9q8U", "images": [{"url": "https://i.scdn.co/image/ab67616d0000b273441f17f7869072d3862462bb", "height": 640, "width": 640}, {"url": "https://i.scdn.co/image/ab67616d00001e02441f17f7869072d3862462bb", "height": 300, "width": 300}, {"url": "https://i.scdn.co/image/ab67616d00004851441f17f7869072d3862462bb", "height": 64, "width": 64}], "name": "Hrithik Roshan", "popularity": 49, "type": "artist", "uri": "spotify:artist:5TWDvkVWG1vayan1QA9q8U"}, {"external_urls": {"spotify": "https://open.spotify.com/artist/1WTFOsRsg1Vzx5NzyE53JR"}, "followers": {"href": null, "total": 3333}, "genres": ["bollywood", "desi"], "href": "https://api.spotify.com/v1/artists/1WTFOsRsg1Vzx5NzyE53JR", "id": "1WTFOsRsg1Vzx5NzyE53JR", "images": [], "name": "Abhay Deol", "popularity": 49, "type": "artist", "uri": "spotify:artist:1WTFOsRsg1Vzx5NzyE53JR"}, {"external_urls": {"spotify": "https://open.spotify.com/artist/1BUoAbyYuvOr13MjHqgdOy"}, "followers": {"href": null, "total": 13165}, "genres": ["bollywood", "desi"], "href": "https://api.spotify.com/v1/artists/1BUoAbyYuvOr13MjHqgdOy", "id": "1BUoAbyYuvOr13MjHqgdOy", "images": [{"url": "https://i.scdn.co/image/ab67616d0000b273814505bed7494444d6780fc1", "height": 640, "width": 640}, {"url": "https://i.scdn.co/image/ab67616d00001e02814505bed7494444d6780fc1", "height": 300, "width": 300}, {"url": "https://i.scdn.co/image/ab67616d00004851814505bed7494444d6780fc1", "height": 64, "width": 64}], "name": "Maria Del Mar Fernandez", "popularity": 49, "type": "artist", "uri": "spotify:artist:1BUoAbyYuvOr13MjHqgdOy"}, {"external_urls": {"spotify": "https://open.spotify.com/artist/6ohaQzKaXrobAL8paLSaxq"}, "followers": {"href": null, "total": 2528956}, "genres": ["bollywood", "sufi", "desi", "hindi pop", "qawwali"], "href": "https://api.spotify.com/v1/artists/6ohaQzKaXrobAL8paLSaxq", "id": "6ohaQzKaXrobAL8paLSaxq", "images": [{"url": "https://i.scdn.co/image/ab6761610000e5eb13a6f2195deea1f736d046e4", "height": 640, "width": 640}, {"url": "https://i.scdn.co/image/ab6761610000517413a6f2195deea1f736d046e4", "height": 320, "width": 320}, {"url": "https://i.scdn.co/image/ab6761610000f17813a6f2195deea1f736d046e4", "height": 160, "width": 160}], "name": "Salim\u2013Sulaiman", "popularity": 71, "type": "artist", "uri": "spotify:artist:6ohaQzKaXrobAL8paLSaxq"}, {"external_urls": {"spotify": "https://open.spotify.com/artist/1EzHkoB4160h1B1xAyXSUR"}, "followers": {"href": null, "total": 166468}, "genres": ["bollywood", "bhajan"], "href": "https://api.spotify.com/v1/artists/1EzHkoB4160h1B1xAyXSUR", "id": "1EzHkoB4160h1B1xAyXSUR", "images": [{"url": "https://i.scdn.co/image/ab6761610000e5eb64260d69859a5368ec508f98", "height": 640, "width": 640}, {"url": "https://i.scdn.co/image/ab6761610000517464260d69859a5368ec508f98", "height": 320, "width": 320}, {"url": "https://i.scdn.co/image/ab6761610000f17864260d69859a5368ec508f98", "height": 160, "width": 160}], "name": "Piyush Mishra", "popularity": 59, "type": "artist", "uri": "spotify:artist:1EzHkoB4160h1B1xAyXSUR"}, {"external_urls": {"spotify": "https://open.spotify.com/artist/0L5GV6LN8SWWUWIdBbTLTZ"}, "followers": {"href": null, "total": 7815309}, "genres": ["bollywood", "sufi", "desi", "hindi pop"], "href": "https://api.spotify.com/v1/artists/0L5GV6LN8SWWUWIdBbTLTZ", "id": "0L5GV6LN8SWWUWIdBbTLTZ", "images": [{"url": "https://i.scdn.co/image/ab6761610000e5eb3db0499a689aa9b4a47ebba3", "height": 640, "width": 640}, {"url": "https://i.scdn.co/image/ab676161000051743db0499a689aa9b4a47ebba3", "height": 320, "width": 320}, {"url": "https://i.scdn.co/image/ab6761610000f1783db0499a689aa9b4a47ebba3", "height": 160, "width": 160}], "name": "Shankar-Ehsaan-Loy", "popularity": 76, "type": "artist", "uri": "spotify:artist:0L5GV6LN8SWWUWIdBbTLTZ"}, {"external_urls": {"spotify": "https://open.spotify.com/artist/5cB4d4jPYjMT326sjihQ4m"}, "followers": {"href": null, "total": 9017104}, "genres": ["bollywood", "hindi pop", "desi", "bangla pop"], "href": "https://api.spotify.com/v1/artists/5cB4d4jPYjMT326sjihQ4m", "id": "5cB4d4jPYjMT326sjihQ4m", "images": [{"url": "https://i.scdn.co/image/ab6761610000e5eb2573d940f1062a6646891e50", "height": 640, "width": 640}, {"url": "https://i.scdn.co/image/ab676161000051742573d940f1062a6646891e50", "height": 320, "width": 320}, {"url": "https://i.scdn.co/image/ab6761610000f1782573d940f1062a6646891e50", "height": 160, "width": 160}], "name": "Shaan", "popularity": 72, "type": "artist", "uri": "spotify:artist:5cB4d4jPYjMT326sjihQ4m"}, {"external_urls": {"spotify": "https://open.spotify.com/artist/0Yb0T3wUUNiIvHjqnfkbuH"}, "followers": {"href": null, "total": 439056}, "genres": ["bollywood", "desi"], "href": "https://api.spotify.com/v1/artists/0Yb0T3wUUNiIvHjqnfkbuH", "id": "0Yb0T3wUUNiIvHjqnfkbuH", "images": [{"url": "https://i.scdn.co/image/ab6761610000e5eb917bf7b3a0d7e8621a0bbed0", "height": 640, "width": 640}, {"url": "https://i.scdn.co/image/ab67616100005174917bf7b3a0d7e8621a0bbed0", "height": 320, "width": 320}, {"url": "https://i.scdn.co/image/ab6761610000f178917bf7b3a0d7e8621a0bbed0", "height": 160, "width": 160}], "name": "Mahalakshmi Iyer", "popularity": 70, "type": "artist", "uri": "spotify:artist:0Yb0T3wUUNiIvHjqnfkbuH"}, {"external_urls": {"spotify": "https://open.spotify.com/artist/4YgUVg4p7xtMOrOS4GjiJZ"}, "followers": {"href": null, "total": 439724}, "genres": ["bollywood", "hindi pop", "desi"], "href": "https://api.spotify.com/v1/artists/4YgUVg4p7xtMOrOS4GjiJZ", "id": "4YgUVg4p7xtMOrOS4GjiJZ", "images": [{"url": "https://i.scdn.co/image/ab6761610000e5eb1dc3081fe7fea3d0e55f3d85", "height": 640, "width": 640}, {"url": "https://i.scdn.co/image/ab676161000051741dc3081fe7fea3d0e55f3d85", "height": 320, "width": 320}, {"url": "https://i.scdn.co/image/ab6761610000f1781dc3081fe7fea3d0e55f3d85", "height": 160, "width": 160}], "name": "Jatin-Lalit", "popularity": 73, "type": "artist", "uri": "spotify:artist:4YgUVg4p7xtMOrOS4GjiJZ"}, {"external_urls": {"spotify": "https://open.spotify.com/artist/5l1aGNGCRGomCMHVufh6xC"}, "followers": {"href": null, "total": 1074430}, "genres": ["bollywood"], "href": "https://api.spotify.com/v1/artists/5l1aGNGCRGomCMHVufh6xC", "id": "5l1aGNGCRGomCMHVufh6xC", "images": [{"url": "https://i.scdn.co/image/ab67616d0000b2736cebb457f1b913149a308665", "height": 640, "width": 640}, {"url": "https://i.scdn.co/image/ab67616d00001e026cebb457f1b913149a308665", "height": 300, "width": 300}, {"url": "https://i.scdn.co/image/ab67616d000048516cebb457f1b913149a308665", "height": 64, "width": 64}], "name": "Amit Kumar", "popularity": 62, "type": "artist", "uri": "spotify:artist:5l1aGNGCRGomCMHVufh6xC"}, {"external_urls": {"spotify": "https://open.spotify.com/artist/1dVygo6tRFXC8CSWURQJq2"}, "followers": {"href": null, "total": 22034668}, "genres": ["kannada pop", "bollywood", "sandalwood", "hindi pop", "desi", "marathi pop"], "href": "https://api.spotify.com/v1/artists/1dVygo6tRFXC8CSWURQJq2", "id": "1dVygo6tRFXC8CSWURQJq2", "images": [{"url": "https://i.scdn.co/image/ab6761610000e5ebbc959d7569618ec2af2210f5", "height": 640, "width": 640}, {"url": "https://i.scdn.co/image/ab67616100005174bc959d7569618ec2af2210f5", "height": 320, "width": 320}, {"url": "https://i.scdn.co/image/ab6761610000f178bc959d7569618ec2af2210f5", "height": 160, "width": 160}], "name": "Sonu Nigam", "popularity": 81, "type": "artist", "uri": "spotify:artist:1dVygo6tRFXC8CSWURQJq2"}, {"external_urls": {"spotify": "https://open.spotify.com/artist/3gBKY0y3dFFVRqicLnVZYz"}, "followers": {"href": null, "total": 19571833}, "genres": ["bollywood", "hindi pop", "desi"], "href": "https://api.spotify.com/v1/artists/3gBKY0y3dFFVRqicLnVZYz", "id": "3gBKY0y3dFFVRqicLnVZYz", "images": [{"url": "https://i.scdn.co/image/ab6761610000e5eb935b2dd507212bd72a71d7f9", "height": 640, "width": 640}, {"url": "https://i.scdn.co/image/ab67616100005174935b2dd507212bd72a71d7f9", "height": 320, "width": 320}, {"url": "https://i.scdn.co/image/ab6761610000f178935b2dd507212bd72a71d7f9", "height": 160, "width": 160}], "name": "Alka Yagnik", "popularity": 84, "type": "artist", "uri": "spotify:artist:3gBKY0y3dFFVRqicLnVZYz"}, {"external_urls": {"spotify": "https://open.spotify.com/artist/6WPmTGeeoymoVlXVtsCwz7"}, "followers": {"href": null, "total": 3858166}, "genres": ["bollywood", "gujarati garba", "hindi pop"], "href": "https://api.spotify.com/v1/artists/6WPmTGeeoymoVlXVtsCwz7", "id": "6WPmTGeeoymoVlXVtsCwz7", "images": [{"url": "https://i.scdn.co/image/ab6761610000e5eb4f1d4019906979d45f7200a3", "height": 640, "width": 640}, {"url": "https://i.scdn.co/image/ab676161000051744f1d4019906979d45f7200a3", "height": 320, "width": 320}, {"url": "https://i.scdn.co/image/ab6761610000f1784f1d4019906979d45f7200a3", "height": 160, "width": 160}], "name": "Kavita Krishnamurthy", "popularity": 72, "type": "artist", "uri": "spotify:artist:6WPmTGeeoymoVlXVtsCwz7"}, {"external_urls": {"spotify": "https://open.spotify.com/artist/7uIbLdzzSEqnX0Pkrb56cR"}, "followers": {"href": null, "total": 33170714}, "genres": ["bollywood", "hindi hip hop", "desi", "hindi pop", "punjabi pop"], "href": "https://api.spotify.com/v1/artists/7uIbLdzzSEqnX0Pkrb56cR", "id": "7uIbLdzzSEqnX0Pkrb56cR", "images": [{"url": "https://i.scdn.co/image/ab6761610000e5ebbc7e4fffd515b47ff1ebbc1f", "height": 640, "width": 640}, {"url": "https://i.scdn.co/image/ab67616100005174bc7e4fffd515b47ff1ebbc1f", "height": 320, "width": 320}, {"url": "https://i.scdn.co/image/ab6761610000f178bc7e4fffd515b47ff1ebbc1f", "height": 160, "width": 160}], "name": "Yo Yo Honey Singh", "popularity": 80, "type": "artist", "uri": "spotify:artist:7uIbLdzzSEqnX0Pkrb56cR"}, {"external_urls": {"spotify": "https://open.spotify.com/artist/5sifufajls8Q6k04Y4F8mH"}, "followers": {"href": null, "total": 169643}, "genres": ["bollywood", "desi", "hindi pop"], "href": "https://api.spotify.com/v1/artists/5sifufajls8Q6k04Y4F8mH", "id": "5sifufajls8Q6k04Y4F8mH", "images": [{"url": "https://i.scdn.co/image/ab6761610000e5eb712422ace09f38b6e592fd17", "height": 640, "width": 640}, {"url": "https://i.scdn.co/image/ab67616100005174712422ace09f38b6e592fd17", "height": 320, "width": 320}, {"url": "https://i.scdn.co/image/ab6761610000f178712422ace09f38b6e592fd17", "height": 160, "width": 160}], "name": "Sameer Anjaan", "popularity": 67, "type": "artist", "uri": "spotify:artist:5sifufajls8Q6k04Y4F8mH"}, {"external_urls": {"spotify": "https://open.spotify.com/artist/0FJz7XR37hH69traaHLijA"}, "followers": {"href": null, "total": 2244482}, "genres": ["bollywood", "hindi pop", "desi"], "href": "https://api.spotify.com/v1/artists/0FJz7XR37hH69traaHLijA", "id": "0FJz7XR37hH69traaHLijA", "images": [{"url": "https://i.scdn.co/image/ab6761610000e5eb2fc11c068e71fdc6f848d1ab", "height": 640, "width": 640}, {"url": "https://i.scdn.co/image/ab676161000051742fc11c068e71fdc6f848d1ab", "height": 320, "width": 320}, {"url": "https://i.scdn.co/image/ab6761610000f1782fc11c068e71fdc6f848d1ab", "height": 160, "width": 160}], "name": "Shaarib Toshi", "popularity": 70, "type": "artist", "uri": "spotify:artist:0FJz7XR37hH69traaHLijA"}, {"external_urls": {"spotify": "https://open.spotify.com/artist/4fEkbug6kZzzJ8eYX6Kbbp"}, "followers": {"href": null, "total": 21320116}, "genres": ["bollywood", "hindi pop", "desi"], "href": "https://api.spotify.com/v1/artists/4fEkbug6kZzzJ8eYX6Kbbp", "id": "4fEkbug6kZzzJ8eYX6Kbbp", "images": [{"url": "https://i.scdn.co/image/ab6761610000e5ebb09a31f853166e721d4d46b2", "height": 640, "width": 640}, {"url": "https://i.scdn.co/image/ab67616100005174b09a31f853166e721d4d46b2", "height": 320, "width": 320}, {"url": "https://i.scdn.co/image/ab6761610000f178b09a31f853166e721d4d46b2", "height": 160, "width": 160}], "name": "KK", "popularity": 81, "type": "artist", "uri": "spotify:artist:4fEkbug6kZzzJ8eYX6Kbbp"}, {"external_urls": {"spotify": "https://open.spotify.com/artist/3KDhyMTFZlrfAO0zK18z4t"}, "followers": {"href": null, "total": 514425}, "genres": ["bhangra", "desi", "desi pop", "punjabi pop", "punjabi hip hop"], "href": "https://api.spotify.com/v1/artists/3KDhyMTFZlrfAO0zK18z4t", "id": "3KDhyMTFZlrfAO0zK18z4t", "images": [{"url": "https://i.scdn.co/image/ab6761610000e5eb39b00ce5cc8dded985723b4f", "height": 640, "width": 640}, {"url": "https://i.scdn.co/image/ab6761610000517439b00ce5cc8dded985723b4f", "height": 320, "width": 320}, {"url": "https://i.scdn.co/image/ab6761610000f17839b00ce5cc8dded985723b4f", "height": 160, "width": 160}], "name": "Mickey Singh", "popularity": 52, "type": "artist", "uri": "spotify:artist:3KDhyMTFZlrfAO0zK18z4t"}, {"external_urls": {"spotify": "https://open.spotify.com/artist/5WjtMDHV7iUbAtMysxZ1AB"}, "followers": {"href": null, "total": 3218}, "genres": ["bhangra", "desi"], "href": "https://api.spotify.com/v1/artists/5WjtMDHV7iUbAtMysxZ1AB", "id": "5WjtMDHV7iUbAtMysxZ1AB", "images": [{"url": "https://i.scdn.co/image/ab67616d0000b273309390cccf21a2223b380f91", "height": 640, "width": 640}, {"url": "https://i.scdn.co/image/ab67616d00001e02309390cccf21a2223b380f91", "height": 300, "width": 300}, {"url": "https://i.scdn.co/image/ab67616d00004851309390cccf21a2223b380f91", "height": 64, "width": 64}], "name": "Sunny Brown", "popularity": 25, "type": "artist", "uri": "spotify:artist:5WjtMDHV7iUbAtMysxZ1AB"}, {"external_urls": {"spotify": "https://open.spotify.com/artist/7nMU4JggY9X3ufAlZ3Q2b2"}, "followers": {"href": null, "total": 1344}, "genres": [], "href": "https://api.spotify.com/v1/artists/7nMU4JggY9X3ufAlZ3Q2b2", "id": "7nMU4JggY9X3ufAlZ3Q2b2", "images": [{"url": "https://i.scdn.co/image/ab67616d0000b273999b73b34dde26f8552d8470", "height": 640, "width": 640}, {"url": "https://i.scdn.co/image/ab67616d00001e02999b73b34dde26f8552d8470", "height": 300, "width": 300}, {"url": "https://i.scdn.co/image/ab67616d00004851999b73b34dde26f8552d8470", "height": 64, "width": 64}], "name": "Fateh Doe", "popularity": 23, "type": "artist", "uri": "spotify:artist:7nMU4JggY9X3ufAlZ3Q2b2"}]}