{"tracks": {"href": "https://api.spotify.com/v1/search?offset=0&limit=50&query=rainy%20late%20night%20drive%20year%3A2010-2025&type=track&market=US", "limit": 50, "next": null, "offset": 0, "previous": null, "total": 8, "items": [{"album": {"album_type": "album", "artists": [{"external_urls": {"spotify": "https://open.spotify.com/artist/6Whcf7FyfxxeW8tDkw1Y3v"}, "href": "https://api.spotify.com/v1/artists/6Whcf7FyfxxeW8tDkw1Y3v", "id": "6Whcf7FyfxxeW8tDkw1Y3v", "name": "Ar\u0113n", "type": "artist", "uri": "spotify:artist:6Whcf7FyfxxeW8tDkw1Y3v"}], "external_urls": {"spotify": "https://open.spotify.com/album/6sCw6OfMIcpt76lW7nHWjC"}, "href": "https://api.spotify.com/v1/albums/6sCw6OfMIcpt76lW7nHWjC", "id": "6sCw6OfMIcpt76lW7nHWjC", "images": [{"height": 640, "width": 640, "url": "https://i.scdn.co/image/ab67616d0000b273c4df8856ec89e61a7744fe8e"}, {"height": 300, "width": 300, "url": "https://i.scdn.co/image/ab67616d00001e02c4df8856ec89e61a7744fe8e"}, {"height": 64, "width": 64, "url": "https://i.scdn.co/image/ab67616d00004851c4df8856ec89e61a7744fe8e"}], "is_playable": true, "name": "Late night drive", "release_date": "2023-09-12", "release_date_precision": "day", "total_tracks": 7, "type": "album", "uri": "spotify:album:6sCw6OfMIcpt76lW7nHWjC"}, "artists": [{"external_urls": {"spotify": "https://open.spotify.com/artist/6Whcf7FyfxxeW8tDkw1Y3v"}, "href": "https://api.spotify.com/v1/artists/6Whcf7FyfxxeW8tDkw1Y3v", "id": "6Whcf7FyfxxeW8tDkw1Y3v", "name": "Ar\u0113n", "type": "artist", "uri": "spotify:artist:6Whcf7FyfxxeW8tDkw1Y3v"}], "disc_number": 1, "duration_ms": 154000, "explicit": false, "external_ids": {"isrc": "SE6XY2330233"}, "external_urls": {"spotify": "https://open.spotify.com/track/6scMBiHuF9YPvBTRmFaKdC"}, "href": "https://api.spotify.com/v1/tracks/6scMBiHuF9YPvBTRmFaKdC", "id": "6scMBiHuF9YPvBTRmFaKdC", "is_local": false, "is_playable": true, "name": "Rainy fall", "popularity": 14, "preview_url": null, "track_number": 6, "type": "track", "uri": "spotify:track:6scMBiHuF9YPvBTRmFaKdC"}, {"album": {"album_type": "album", "artists": [{"external_urls": {"spotify": "https://open.spotify.com/artist/6Whcf7FyfxxeW8tDkw1Y3v"}, "href": "https://api.spotify.com/v1/artists/6Whcf7FyfxxeW8tDkw1Y3v", "id": "6Whcf7FyfxxeW8tDkw1Y3v", "name": "Ar\u0113n", "type": "artist", "uri": "spotify:artist:6Whcf7FyfxxeW8tDkw1Y3v"}], "external_urls": {"spotify": "https://open.spotify.com/album/6sCw6OfMIcpt76lW7nHWjC"}, "href": "https://api.spotify.com/v1/albums/6sCw6OfMIcpt76lW7nHWjC", "id": "6sCw6OfMIcpt76lW7nHWjC", "images": [{"height": 640, "width": 640, "url": "https://i.scdn.co/image/ab67616d0000b273c4df8856ec89e61a7744fe8e"}, {"height": 300, "width": 300, "url": "https://i.scdn.co/image/ab67616d00001e02c4df8856ec89e61a7744fe8e"}, {"height": 64, "width": 64, "url": "https://i.scdn.co/image/ab67616d00004851c4df8856ec89e61a7744fe8e"}], "is_playable": true, "name": "Late night drive", "release_date": "2023-09-12", "release_date_precision": "day", "total_tracks": 7, "type": "album", "uri": "spotify:album:6sCw6OfMIcpt76lW7nHWjC"}, "artists": [{"external_urls": {"spotify": "https://open.spotify.com/artist/6Whcf7FyfxxeW8tDkw1Y3v"}, "href": "https://api.spotify.com/v1/artists/6Whcf7FyfxxeW8tDkw1Y3v", "id": "6Whcf7FyfxxeW8tDkw1Y3v", "name": "Ar\u0113n", "type": "artist", "uri": "spotify:artist:6Whcf7FyfxxeW8tDkw1Y3v"}], "disc_number": 1, "duration_ms": 127500, "explicit": false, "external_ids": {"isrc": "SE6XW2313396"}, "external_urls": {"spotify": "https://open.spotify.com/track/3DCNL85u6SLdvhPQSjjF2o"}, "href": "https://api.spotify.com/v1/tracks/3DCNL85u6SLdvhPQSjjF2o", "id": "3DCNL85u6SLdvhPQSjjF2o", "is_local": false, "is_playable": true, "name": "Reading on a rainy day", "popularity": 15, "preview_url": null, "track_number": 5, "type": "track", "uri": "spotify:track:3DCNL85u6SLdvhPQSjjF2o"}, {"album": {"album_type": "album", "artists": [{"external_urls": {"spotify": "https://open.spotify.com/artist/3zw9kN0i8eKIDbGhEiIIwo"}, "href": "https://api.spotify.com/v1/artists/3zw9kN0i8eKIDbGhEiIIwo", "id": "3zw9kN0i8eKIDbGhEiIIwo", "name": "Lofi Hip-Hop Beats", "type": "artist", "uri": "spotify:artist:3zw9kN0i8eKIDbGhEiIIwo"}, {"external_urls": {"spotify": "https://open.spotify.com/artist/3bGlbsO6n02a6ziALbZwQj"}, "href": "https://api.spotify.com/v1/artists/3bGlbsO6n02a6ziALbZwQj", "id": "3bGlbsO6n02a6ziALbZwQj", "name": "Midnight Lofi", "type": "artist", "uri": "spotify:artist:3bGlbsO6n02a6ziALbZwQj"}, {"external_urls": {"spotify": "https://open.spotify.com/artist/6O9dbU0gri3cUCz3yFs2I5"}, "href": "https://api.spotify.com/v1/artists/6O9dbU0gri3cUCz3yFs2I5", "id": "6O9dbU0gri3cUCz3yFs2I5", "name": "Copyright Free Lofi", "type": "artist", "uri": "spotify:artist:6O9dbU0gri3cUCz3yFs2I5"}], "external_urls": {"spotify": "https://open.spotify.com/album/2jFgQHI6Dy4SRt2ENekvSx"}, "href": "https://api.spotify.com/v1/albums/2jFgQHI6Dy4SRt2ENekvSx", "id": "2jFgQHI6Dy4SRt2ENekvSx", "images": [{"height": 640, "width": 640, "url": "https://i.scdn.co/image/ab67616d0000b27305524f22821c07935b065e99"}, {"height": 300, "width": 300, "url": "https://i.scdn.co/image/ab67616d00001e0205524f22821c07935b065e99"}, {"height": 64, "width": 64, "url": "https://i.scdn.co/image/ab67616d0000485105524f22821c07935b065e99"}], "is_playable": true, "name": "Lofi Chill for Late Night Drives", "release_date": "2025-04-13", "release_date_precision": "day", "total_tracks": 7, "type": "album", "uri": "spotify:album:2jFgQHI6Dy4SRt2ENekvSx"}, "artists": [{"external_urls": {"spotify": "https://open.spotify.com/artist/3zw9kN0i8eKIDbGhEiIIwo"}, "href": "https://api.spotify.com/v1/artists/3zw9kN0i8eKIDbGhEiIIwo", "id": "3zw9kN0i8eKIDbGhEiIIwo", "name": "Lofi Hip-Hop Beats", "type": "artist", "uri": "spotify:artist:3zw9kN0i8eKIDbGhEiIIwo"}, {"external_urls": {"spotify": "https://open.spotify.com/artist/3bGlbsO6n02a6ziALbZwQj"}, "href": "https://api.spotify.com/v1/artists/3bGlbsO6n02a6ziALbZwQj", "id": "3bGlbsO6n02a6ziALbZwQj", "name": "Midnight Lofi", "type": "artist", "uri": "spotify:artist:3bGlbsO6n02a6ziALbZwQj"}, {"external_urls": {"spotify": "https://open.spotify.com/artist/6O9dbU0gri3cUCz3yFs2I5"}, "href": "https://api.spotify.com/v1/artists/6O9dbU0gri3cUCz3yFs2I5", "id": "6O9dbU0gri3cUCz3yFs2I5", "name": "Copyright Free Lofi", "type": "artist", "uri": "spotify:artist:6O9dbU0gri3cUCz3yFs2I5"}], "disc_number": 1, "duration_ms": 140040, "explicit": false, "external_ids": {"isrc": "QZP7F2560732"}, "external_urls": {"spotify": "https://open.spotify.com/track/4I9I3xdlChnmhXIr6dbX7Y"}, "href": "https://api.spotify.com/v1/tracks/4I9I3xdlChnmhXIr6dbX7Y", "id": "4I9I3xdlChnmhXIr6dbX7Y", "is_local": false, "is_playable": true, "name": "Rainy Day Lofi Soundtrack", "popularity": 5, "preview_url": null, "track_number": 3, "type": "track", "uri": "spotify:track:4I9I3xdlChnmhXIr6dbX7Y"}, {"album": {"album_type": "single", "artists": [{"external_urls": {"spotify": "https://open.spotify.com/artist/3UtsfdwtDytXoZzQWNcjaH"}, "href": "https://api.spotify.com/v1/artists/3UtsfdwtDytXoZzQWNcjaH", "id": "3UtsfdwtDytXoZzQWNcjaH", "name": "Out of Townerz", "type": "artist", "uri": "spotify:artist:3UtsfdwtDytXoZzQWNcjaH"}], "external_urls": {"spotify": "https://open.spotify.com/album/4N04vxZbrTs9AfDeatWlFD"}, "href": "https://api.spotify.com/v1/albums/4N04vxZbrTs9AfDeatWlFD", "id": "4N04vxZbrTs9AfDeatWlFD", "images": [{"height": 640, "width": 640, "url": "https://i.scdn.co/image/ab67616d0000b273f83c4677cd60134473bf0a47"}, {"height": 300, "width": 300, "url": "https://i.scdn.co/image/ab67616d00001e02f83c4677cd60134473bf0a47"}, {"height": 64, "width": 64, "url": "https://i.scdn.co/image/ab67616d00004851f83c4677cd60134473bf0a47"}], "is_playable": true, "name": "Late Night Drive", "release_date": "2020-11-27", "release_date_precision": "day", "total_tracks": 6, "type": "album", "uri": "spotify:album:4N04vxZbrTs9AfDeatWlFD"}, "artists": [{"external_urls": {"spotify": "https://open.spotify.com/artist/3UtsfdwtDytXoZzQWNcjaH"}, "href": "https://api.spotify.com/v1/artists/3UtsfdwtDytXoZzQWNcjaH", "id": "3UtsfdwtDytXoZzQWNcjaH", "name": "Out of Townerz", "type": "artist", "uri": "spotify:artist:3UtsfdwtDytXoZzQWNcjaH"}, {"external_urls": {"spotify": "https://open.spotify.com/artist/3JnTSWOADlL9VjkQs3oON4"}, "href": "https://api.spotify.com/v1/artists/3JnTSWOADlL9VjkQs3oON4", "id": "3JnTSWOADlL9VjkQs3oON4", "name": "Dee Miinor", "type": "artist", "uri": "spotify:artist:3JnTSWOADlL9VjkQs3oON4"}, {"external_urls": {"spotify": "https://open.spotify.com/artist/4aOctpfT4GvLX0i04gBgZr"}, "href": "https://api.spotify.com/v1/artists/4aOctpfT4GvLX0i04gBgZr", "id": "4aOctpfT4GvLX0i04gBgZr", "name": "King Corona", "type": "artist", "uri": "spotify:artist:4aOctpfT4GvLX0i04gBgZr"}], "disc_number": 1, "duration_ms": 135433, "explicit": false, "external_ids": {"isrc": "QZNWR2081543"}, "external_urls": {"spotify": "https://open.spotify.com/track/4pNWMj3WzNWU09S69Lf0K7"}, "href": "https://api.spotify.com/v1/tracks/4pNWMj3WzNWU09S69Lf0K7", "id": "4pNWMj3WzNWU09S69Lf0K7", "is_local": false, "is_playable": true, "name": "Rainy Nights", "popularity": 0, "preview_url": null, "track_number": 3, "type": "track", "uri": "spotify:track:4pNWMj3WzNWU09S69Lf0K7"}, {"album": {"album_type": "album", "artists": [{"external_urls": {"spotify": "https://open.spotify.com/artist/0tERDsa8SRKhq06BTARDhR"}, "href": "https://api.spotify.com/v1/artists/0tERDsa8SRKhq06BTARDhR", "id": "0tERDsa8SRKhq06BTARDhR", "name": "NomadSoul LoFi", "type": "artist", "uri": "spotify:artist:0tERDsa8SRKhq06BTARDhR"}], "external_urls": {"spotify": "https://open.spotify.com/album/4i5RCeHgNWyZMt3zWtXXCA"}, "href": "https://api.spotify.com/v1/albums/4i5RCeHgNWyZMt3zWtXXCA", "id": "4i5RCeHgNWyZMt3zWtXXCA", "images": [{"height": 640, "width": 640, "url": "https://i.scdn.co/image/ab67616d0000b273462f3113b17a8639fb45ec43"}, {"height": 300, "width": 300, "url": "https://i.scdn.co/image/ab67616d00001e02462f3113b17a8639fb45ec43"}, {"height": 64, "width": 64, "url": "https://i.scdn.co/image/ab67616d00004851462f3113b17a8639fb45ec43"}], "is_playable": true, "name": "Rainy City Nights", "release_date": "2025-01-24", "release_date_precision": "day", "total_tracks": 10, "type": "album", "uri": "spotify:album:4i5RCeHgNWyZMt3zWtXXCA"}, "artists": [{"external_urls": {"spotify": "https://open.spotify.com/artist/0tERDsa8SRKhq06BTARDhR"}, "href": "https://api.spotify.com/v1/artists/0tERDsa8SRKhq06BTARDhR", "id": "0tERDsa8SRKhq06BTARDhR", "name": "NomadSoul LoFi", "type": "artist", "uri": "spotify:artist:0tERDsa8SRKhq06BTARDhR"}], "disc_number": 1, "duration_ms": 178199, "explicit": false, "external_ids": {"isrc": "CAHQJ2553566"}, "external_urls": {"spotify": "https://open.spotify.com/track/4057IT9satieFq6iQU8yM6"}, "href": "https://api.spotify.com/v1/tracks/4057IT9satieFq6iQU8yM6", "id": "4057IT9satieFq6iQU8yM6", "is_local": false, "is_playable": true, "name": "Late Night Drive", "popularity": 0, "preview_url": null, "track_number": 4, "type": "track", "uri": "spotify:track:4057IT9satieFq6iQU8yM6"}, {"album": {"album_type": "album", "artists": [{"external_urls": {"spotify": "https://open.spotify.com/artist/55PvWER0tfWvDQUVoh3s2S"}, "href": "https://api.spotify.com/v1/artists/55PvWER0tfWvDQUVoh3s2S", "id": "55PvWER0tfWvDQUVoh3s2S", "name": "XHX", "type": "artist", "uri": "spotify:artist:55PvWER0tfWvDQUVoh3s2S"}], "external_urls": {"spotify": "https://open.spotify.com/album/5I2xFiaJ6RGP1j3IiVgLdD"}, "href": "https://api.spotify.com/v1/albums/5I2xFiaJ6RGP1j3IiVgLdD", "id": "5I2xFiaJ6RGP1j3IiVgLdD", "images": [{"height": 640, "width": 640, "url": "https://i.scdn.co/image/ab67616d0000b273c9fbf37dd3bdcfbdcda2e72f"}, {"height": 300, "width": 300, "url": "https://i.scdn.co/image/ab67616d00001e02c9fbf37dd3bdcfbdcda2e72f"}, {"height": 64, "width": 64, "url": "https://i.scdn.co/image/ab67616d00004851c9fbf37dd3bdcfbdcda2e72f"}], "is_playable": true, "name": "rainy day thoughts", "release_date": "2024-09-20", "release_date_precision": "day", "total_tracks": 10, "type": "album", "uri": "spotify:album:5I2xFiaJ6RGP1j3IiVgLdD"}, "artists": [{"external_urls": {"spotify": "https://open.spotify.com/artist/55PvWER0tfWvDQUVoh3s2S"}, "href": "https://api.spotify.com/v1/artists/55PvWER0tfWvDQUVoh3s2S", "id": "55PvWER0tfWvDQUVoh3s2S", "name": "XHX", "type": "artist", "uri": "spotify:artist:55PvWER0tfWvDQUVoh3s2S"}], "disc_number": 1, "duration_ms": 75169, "explicit": false, "external_ids": {"isrc": "UKU932426603"}, "external_urls": {"spotify": "https://open.spotify.com/track/0FtmzkCrqmezPPN0cAIx5k"}, "href": "https://api.spotify.com/v1/tracks/0FtmzkCrqmezPPN0cAIx5k", "id": "0FtmzkCrqmezPPN0cAIx5k", "is_local": false, "is_playable": true, "name": "late night drive", "popularity": 0, "preview_url": null, "track_number": 4, "type": "track", "uri": "spotify:track:0FtmzkCrqmezPPN0cAIx5k"}, {"album": {"album_type": "compilation", "artists": [{"external_urls": {"spotify": "https://open.spotify.com/artist/0LyfQWJT6nXafLPZqxe9Of"}, "href": "https://api.spotify.com/v1/artists/0LyfQWJT6nXafLPZqxe9Of", "id": "0LyfQWJT6nXafLPZqxe9Of", "name": "Various Artists", "type": "artist", "uri": "spotify:artist:0LyfQWJT6nXafLPZqxe9Of"}], "external_urls": {"spotify": "https://open.spotify.com/album/6I5bVqZSNHVUXTRM7KNU9Y"}, "href": "https://api.spotify.com/v1/albums/6I5bVqZSNHVUXTRM7KNU9Y", "id": "6I5bVqZSNHVUXTRM7KNU9Y", "images": [{"height": 640, "width": 640, "url": "https://i.scdn.co/image/ab67616d0000b273424d7c53632bbf8fda612b11"}, {"height": 300, "width": 300, "url": "https://i.scdn.co/image/ab67616d00001e02424d7c53632bbf8fda612b11"}, {"height": 64, "width": 64, "url": "https://i.scdn.co/image/ab67616d00004851424d7c53632bbf8fda612b11"}], "is_playable": true, "name": "Rainy Day Mood, Set 3", "release_date": "2021-07-28", "release_date_precision": "day", "total_tracks": 20, "type": "album", "uri": "spotify:album:6I5bVqZSNHVUXTRM7KNU9Y"}, "artists": [{"external_urls": {"spotify": "https://open.spotify.com/artist/6TwIqs12VlcWHYNhWDwdKY"}, "href": "https://api.spotify.com/v1/artists/6TwIqs12VlcWHYNhWDwdKY", "id": "6TwIqs12VlcWHYNhWDwdKY", "name": "Mark Dorricott", "type": "artist", "uri": "spotify:artist:6TwIqs12VlcWHYNhWDwdKY"}], "disc_number": 1, "duration_ms": 203050, "explicit": false, "external_ids": {"isrc": "US5UL1706563"}, "external_urls": {"spotify": "https://open.spotify.com/track/6hxaGfMO9P8rSYXDgBrIyU"}, "href": "https://api.spotify.com/v1/tracks/6hxaGfMO9P8rSYXDgBrIyU", "id": "6hxaGfMO9P8rSYXDgBrIyU", "is_local": false, "is_playable": true, "name": "Late Night Drive", "popularity": 0, "preview_url": null, "track_number": 6, "type": "track", "uri": "spotify:track:6hxaGfMO9P8rSYXDgBrIyU"}, {"album": {"album_type": "album", "artists": [{"external_urls": {"spotify": "https://open.spotify.com/artist/5dc511ESbzldgFKyMGYnlv"}, "href": "https://api.spotify.com/v1/artists/5dc511ESbzldgFKyMGYnlv", "id": "5dc511ESbzldgFKyMGYnlv", "name": "Bakawai", "type": "artist", "uri": "spotify:artist:5dc511ESbzldgFKyMGYnlv"}], "external_urls": {"spotify": "https://open.spotify.com/album/66ZdNBDxhwH3z4kfkgu56U"}, "href": "https://api.spotify.com/v1/albums/66ZdNBDxhwH3z4kfkgu56U", "id": "66ZdNBDxhwH3z4kfkgu56U", "images": [{"height": 640, "width": 640, "url": "https://i.scdn.co/image/ab67616d0000b27347b4970caa430661bb5af072"}, {"height": 300, "width": 300, "url": "https://i.scdn.co/image/ab67616d00001e0247b4970caa430661bb5af072"}, {"height": 64, "width": 64, "url": "https://i.scdn.co/image/ab67616d0000485147b4970caa430661bb5af072"}], "is_playable": true, "name": "Midnight Driver (Lofi Beats for Late-Night Vibes)", "release_date": "2024-12-18", "release_date_precision": "day", "total_tracks": 14, "type": "album", "uri": "spotify:album:66ZdNBDxhwH3z4kfkgu56U"}, "artists": [{"external_urls": {"spotify": "https://open.spotify.com/artist/5dc511ESbzldgFKyMGYnlv"}, "href": "https://api.spotify.com/v1/artists/5dc511ESbzldgFKyMGYnlv", "id": "5dc511ESbzldgFKyMGYnlv", "name": "Bakawai", "type": "artist", "uri": "spotify:artist:5dc511ESbzldgFKyMGYnlv"}, {"external_urls": {"spotify": "https://open.spotify.com/artist/6545lZ8xKj59HrX5MGyUbG"}, "href": "https://api.spotify.com/v1/artists/6545lZ8xKj59HrX5MGyUbG", "id": "6545lZ8xKj59HrX5MGyUbG", "name": "Dramanova", "type": "artist", "uri": "spotify:artist:6545lZ8xKj59HrX5MGyUbG"}, {"external_urls": {"spotify": "https://open.spotify.com/artist/0fBQMmVCFRw2unqrRReQXJ"}, "href": "https://api.spotify.com/v1/artists/0fBQMmVCFRw2unqrRReQXJ", "id": "0fBQMmVCFRw2unqrRReQXJ", "name": "i like cats", "type": "artist", "uri": "spotify:artist:0fBQMmVCFRw2unqrRReQXJ"}], "disc_number": 1, "duration_ms": 142919, "explicit": false, "external_ids": {"isrc": "QT3EX2471324"}, "external_urls": {"spotify": "https://open.spotify.com/track/0Iz2BaAZ5qCcjusPMFhbFX"}, "href": "https://api.spotify.com/v1/tracks/0Iz2BaAZ5qCcjusPMFhbFX", "id": "0Iz2BaAZ5qCcjusPMFhbFX", "is_local": false, "is_playable": true, "name": "Rainy", "popularity": 0, "preview_url": null, "track_number": 13, "type": "track", "uri": "spotify:track:0Iz2BaAZ5qCcjusPMFhbFX"}]}}